easygan/__init__.py
easygan-0.4.data/scripts/easygan
easygan-0.4.dist-info/METADATA
easygan-0.4.dist-info/RECORD
easygan-0.4.dist-info/WHEEL
easygan-0.4.dist-info/top_level.txt
