Metadata-Version: 2.1
Name: easygan
Version: 0.4
Summary: easygan
Home-page: https://github.com/sleepy-maker/easyGAN
Author: koji kanao
Author-email: kk2796@nyu.edu
License: MIT
Platform: UNKNOWN
Requires-Dist: bs4
Requires-Dist: requests
Requires-Dist: docopt (==0.6.2)
Requires-Dist: keras
Requires-Dist: Pillow
Requires-Dist: numpy
Requires-Dist: lxml
Requires-Dist: tensorflow
